LICENSE.md
README.md
setup.py
ceotr_git_manager/GitFile.py
ceotr_git_manager/GitRepo.py
ceotr_git_manager/GitRepoGitlab.py
ceotr_git_manager/GitRepoRemoteBase.py
ceotr_git_manager/GitUser.py
ceotr_git_manager/__init__.py
ceotr_git_manager.egg-info/PKG-INFO
ceotr_git_manager.egg-info/SOURCES.txt
ceotr_git_manager.egg-info/dependency_links.txt
ceotr_git_manager.egg-info/top_level.txt
ceotr_git_manager.egg-info/zip-safe